<?xml version="1.0" encoding="UTF-8"?>
<!--
To change this template, choose Tools | Templates
and open the template in the editor.
-->
<root>
    <city>
    	<id>0</id>
        <name>Anuradapuraya</name>
            <visit>
		<name>ruwanwali mahasaya</name>
                <cost>0</cost>
		<time>120</time>
            </visit>
            <visit>
		<name>mirisawatiya</name>
                <cost>0</cost>
		<time>90</time>
            </visit>
            <visit>
		<name>abegiriya</name>
                <cost>0</cost>
		<time>100</time>
            </visit>
		
            <meals>
		<name>ABC resturent</name>
                <cost>0</cost>
		<time>30</time>
            </meals>
            <meals>
            	<name>daily inn</name>
                <cost>0</cost>
		<time>30</time>
            </meals>
        
            <bed>
		<name>CDE resturent</name>
		<cost>10000</cost>
            </bed>
            <bed>
            	<name>daily inn</name>
		<cost>6000</cost>
            </bed>
    </city>
    
    <city>
    	<id>1</id>
        <name>Batticaloa</name>
        <visit>
			<name>vatadage</name>
            <cost>0</cost>
			<time>90</time>
        </visit>
        <visit>
			<name>kuttan pokuna</name>
            <cost>0</cost>
			<time>130</time>
        </visit>
        <visit>
			<name>thisa wawa</name>
            <cost>0</cost>
			<time>150</time>
        </visit>
		
        <meals>
			<name>XZ resturent</name>
            <cost>1500</cost>
			<time>30</time>
        </meals>
        <meals>
            <name>daily inn</name>
            <cost>1000</cost>
			<time>60</time>
        </meals>
        
        <bed>
			<name>CDE resturent</name>
			<cost>10000</cost>
        </bed>
        <bed>
            <name>daily inn</name>
			<cost>6000</cost>
        </bed>	
    </city>
	<city>
		<id>2</id>
        <name>Colombo</name>
        <visit>
			<name>vatadage</name>
            <cost>0</cost>
			<time>80</time>
        </visit>
        <visit>
			<name>kuttan pokuna</name>
            <cost>0</cost>
			<time>140</time>
        </visit>
        <visit>
			<name>thisa wawa</name>
            <cost>0</cost>
			<time>60</time>
        </visit>
		
        <meals>
			<name>XZ resturent</name>
            <cost>1500</cost>
			<time>30</time>
        </meals>
        <meals>
            <name>daily inn</name>
            <cost>1000</cost>
			<time>60</time>
        </meals>
        
        <bed>
			<name>CDE resturent</name>
			<cost>10000</cost>
        </bed>
        <bed>
            <name>daily inn</name>
			<cost>6000</cost>
        </bed>		
    </city>
	<city>
		<id>3</id>
        <name>Gall</name>
        <visit>
			<name>vatadage</name>
            <cost>0</cost>
			<time>50</time>
        </visit>
        <visit>
			<name>kuttan pokuna</name>
            <cost>0</cost>
			<time>120</time>
        </visit>
        <visit>
			<name>thisa wawa</name>
            <cost>0</cost>
			<time>150</time>
        </visit>
		
        <meals>
			<name>XZ resturent</name>
            <cost>1500</cost>
			<time>30</time>
        </meals>
        <meals>
            <name>daily inn</name>
            <cost>1000</cost>
			<time>60</time>
        </meals>
        
        <bed>
			<name>CDE resturent</name>
			<cost>10000</cost>
        </bed>
        <bed>
            <name>daily inn</name>
			<cost>6000</cost>
        </bed>		
    </city>
	<city>
		<id>4</id>
        <name>Jaffna</name>
        <visit>
			<name>vatadage</name>
            <cost>0</cost>
			<time>90</time>
        </visit>
        <visit>
			<name>thisa wawa</name>
            <cost>0</cost>
			<time>45</time>
        </visit>
		
        <meals>
			<name>XZ resturent</name>
            <cost>1500</cost>
			<time>30</time>
        </meals>
        <meals>
            <name>daily inn</name>
            <cost>1000</cost>
			<time>60</time>
        </meals>
        <bed>
			<name>CDE resturent</name>
			<cost>10000</cost>
        </bed>
        <bed>
            <name>daily inn</name>
			<cost>6000</cost>
        </bed>
    </city>
	<city>
		<id>5</id>
        <name>Jaffna</name>
        <visit>
			<name>vatadage</name>
            <cost>0</cost>
			<time>80</time>
        </visit>
        <visit>
			<name>thisa wawa</name>
            <cost>0</cost>
			<time>90</time>
        </visit>
		
        <meals>
			<name>XZ resturent</name>
            <cost>1500</cost>
			<time>30</time>
        </meals>
        <meals>
            <name>daily inn</name>
            <cost>1000</cost>
			<time>60</time>
        </meals>
        <bed>
			<name>CDE resturent</name>
			<cost>10000</cost>
        </bed>
        <bed>
            <name>daily inn</name>
			<cost>6000</cost>
        </bed>	
    </city>
	<city>
		<id>6</id>
        <name>Kandy</name>
        <visit>
			<name>vatadage</name>
            <cost>0</cost>
			<time>90</time>
        </visit>
        <visit>
			<name>thisa wawa</name>
            <cost>0</cost>
			<time>40</time>
        </visit>
		
        <meals>
			<name>XZ resturent</name>
            <cost>1500</cost>
			<time>30</time>
        </meals>
        <meals>
            <name>daily inn</name>
            <cost>1000</cost>
			<time>60</time>
        </meals>
        <bed>
			<name>CDE resturent</name>
			<cost>10000</cost>
        </bed>
        <bed>
            <name>daily inn</name>
			<cost>6000</cost>
        </bed>	
    </city>
	<city>
		<id>7</id>
        <name>Mannar</name>
        <visit>
			<name>vatadage</name>
            <cost>0</cost>
			<time>45</time>
        </visit>
        <visit>
			<name>thisa wawa</name>
            <cost>0</cost>
			<time>80</time>
        </visit>
		
        <meals>
			<name>XZ resturent</name>
            <cost>1500</cost>
			<time>30</time>
        </meals>
        <meals>
            <name>daily inn</name>
            <cost>1000</cost>
			<time>60</time>
        </meals>
        <bed>
			<name>CDE resturent</name>
			<cost>10000</cost>
        </bed>
        <bed>
            <name>daily inn</name>
			<cost>6000</cost>
        </bed>	
    </city>
	<city>
		<id>8</id>
        <name>Polonnaruwa</name>
            <visit>
		<name>vatadage</name>
                <cost>0</cost>
		<time>80</time>
            </visit>
            <visit>
		<name>kuttan pokuna</name>
                <cost>0</cost>
		<time>50</time>
            </visit>
            <visit>
		<name>thisa wawa</name>
                <cost>0</cost>
		<time>120</time>
            </visit>
		
            <meals>
		<name>XZ resturent</name>
                <cost>1500</cost>
		<time>30</time>
            </meals>
            <meals>
            	<name>daily inn</name>
                <cost>1000</cost>
		<time>60</time>
            </meals>
        
            <bed>
		<name>CDE resturent</name>
		<cost>10000</cost>
            </bed>
            <bed>
            	<name>daily inn</name>
		<cost>6000</cost>
            </bed>
		
    </city>
    <city>
    	<id>9</id>
        <name>Sinharaja</name>
        <visit>
			<name>vatadage</name>
            <cost>0</cost>
			<time>130</time>
        </visit>
        <visit>
			<name>thisa wawa</name>
            <cost>0</cost>
			<time>300</time>
        </visit>
		
        <meals>
			<name>XZ resturent</name>
            <cost>1500</cost>
			<time>30</time>
        </meals>
        <meals>
            <name>daily inn</name>
            <cost>1000</cost>
			<time>60</time>
        </meals>
        <bed>
			<name>CDE resturent</name>
			<cost>10000</cost>
        </bed>
        <bed>
            <name>daily inn</name>
			<cost>6000</cost>
        </bed>		
    </city>
	<city>
		<id>10</id>
        <name>Trincomalee</name>
        <visit>
			<name>vatadage</name>
            <cost>0</cost>
			<time>60</time>
        </visit>
        <visit>
			<name>thisa wawa</name>
            <cost>0</cost>
			<time>150</time>
        </visit>
		
        <meals>
			<name>XZ resturent</name>
            <cost>1500</cost>
			<time>30</time>
        </meals>
        <meals>
            <name>daily inn</name>
            <cost>1000</cost>
			<time>60</time>
        </meals>
        <bed>
			<name>CDE resturent</name>
			<cost>10000</cost>
        </bed>
        <bed>
            <name>daily inn</name>
			<cost>6000</cost>
        </bed>	
    </city>
	<city>
		<id>11</id>
        <name>Yala</name>
        <visit>
			<name>vatadage</name>
            <cost>0</cost>
			<time>70</time>
        </visit>
        <visit>
			<name>thisa wawa</name>
            <cost>0</cost>
			<time>600</time>
        </visit>
		
        <meals>
			<name>XZ resturent</name>
            <cost>1500</cost>
			<time>30</time>
        </meals>
        <meals>
            <name>daily inn</name>
            <cost>1000</cost>
			<time>60</time>
        </meals>
        <bed>
			<name>CDE resturent</name>
			<cost>10000</cost>
        </bed>
        <bed>
            <name>daily inn</name>
			<cost>6000</cost>
        </bed>	
    </city>
	
        
</root>
